seneca/__init__.py
seneca/Modules/Profile.py
seneca/Modules/__init__.py
seneca/Modules/course.py
seneca/Modules/data.py
seneca/Modules/errors.py
seneca/Modules/info.py
seneca/Modules/key.py
seneca/Modules/memories.py
seneca/Modules/profile.py
seneca/Modules/sessions.py
seneca/Modules/token.py
SenecaPy-2.0.0b9.dist-info/LICENSE
SenecaPy-2.0.0b9.dist-info/METADATA
SenecaPy-2.0.0b9.dist-info/WHEEL
SenecaPy-2.0.0b9.dist-info/top_level.txt
SenecaPy-2.0.0b9.dist-info/RECORD
