Metadata-Version: 2.1
Name: SenecaPy
Version: 2.0.0b9
Summary: senecalearning.com API wrapper
Author: 1azza (Larry Rennoldson)
Author-email: rennoldsonlarry@gmail.com
Keywords: python,cheat,seneca,API,wrapper,requests,senecalearning,senecalearning.com,homework
Classifier: Development Status :: 1 - Planning
Classifier: Intended Audience :: Developers
Classifier: Programming Language :: Python :: 3
Classifier: Operating System :: Unix
Classifier: Operating System :: MacOS :: MacOS X
Classifier: Operating System :: Microsoft :: Windows
License-File: LICENSE
Requires-Dist: requests
Requires-Dist: websocket-client
